pyrestclient/__init__.py
pyrestclient-1.1.9.dist-info/LICENSE
pyrestclient-1.1.9.dist-info/METADATA
pyrestclient-1.1.9.dist-info/WHEEL
pyrestclient-1.1.9.dist-info/top_level.txt
pyrestclient-1.1.9.dist-info/RECORD
