Metadata-Version: 2.1
Name: pyrestclient
Version: 1.1.9
Summary: The simple http client and REST test tool for humans.
Home-page: https://github.com/c-pher/RESTClient.git
Author: Andrey Komissarov
Author-email: a.komisssarov@gmail.com
License: MIT
Classifier: Programming Language :: Python :: 3
Classifier: License :: OSI Approved :: MIT License
Classifier: Operating System :: OS Independent
Classifier: Intended Audience :: System Administrators
Classifier: Intended Audience :: Developers
Classifier: Natural Language :: English
Classifier: Programming Language :: Python :: 3.6
Classifier: Topic :: System :: Systems Administration
Classifier: Topic :: Software Development :: Libraries :: Python Modules
Requires-Python: >=3.6
License-File: LICENSE
Requires-Dist: requests (>=2.22.0)
Requires-Dist: urllib3
Requires-Dist: plogger (>=1.0.6)
